{
    "botSettings": {
        "currentEvent": "none",
        "currencyIcon": "🥕",
        "embedColor": "",
        "timeout": {
            "pagination": "60s"
        }
    },
    "userSettings": {
        "xp": {
            "maxLevel": 50,
            "xpMultiplier": 50,
            "xpRange": {
                "min": 10,
                "max": 250
            }
        },
        "currency": {
            "startingBalance": 250,
            "currencyRange": {
                "min": 10,
                "max": 250
            }
        },
        "chances": {
            "winRandom": 40
        },
        "cooldowns": {
            "drop_1": "5s",
            "drop_2": "5s",
            "drop_3": "5s",
            "drop_4": "5s",
            "drop_weekly": "5s",
            "drop_seasonal": "5s",
            "drop_event": "5s",
            "random": "5s"
        }
    },
    "shopSettings": {
        "stock": [
            1234,
            4321,
            5678,
            8765
        ]
    }
}